zeropython/__init__.py
zeropython/ast_cleaner.py
zeropython/main.py
zeropython/py.typed
zeropython/report.py
zeropython-0.2.0.dist-info/METADATA
zeropython-0.2.0.dist-info/WHEEL
zeropython-0.2.0.dist-info/entry_points.txt
zeropython-0.2.0.dist-info/licenses/LICENSE
zeropython-0.2.0.dist-info/RECORD
