Metadata-Version: 2.3
Name: zeropython
Version: 0.2.0
Summary: Zero Python, a Python library for educational purpose.
Project-URL: Bug Tracker, https://lab.frogg.it/dorianturba/zero-python/-/issues
Project-URL: Homepage, https://lab.frogg.it/dorianturba/zero-python
Author-email: Dorian Turba <zeropython.pip.w1nid@8shield.net>
License: MIT License
License-File: LICENSE
Classifier: Development Status :: 3 - Alpha
Classifier: License :: OSI Approved :: MIT License
Classifier: Operating System :: OS Independent
Classifier: Programming Language :: Python :: 3
Classifier: Programming Language :: Python :: 3.9
Classifier: Programming Language :: Python :: 3.10
Classifier: Programming Language :: Python :: 3.11
Classifier: Programming Language :: Python :: 3.12
Classifier: Programming Language :: Python :: 3.13
Classifier: Typing :: Typed
Requires-Python: >=3.9
Requires-Dist: typer
